RIM_interpret/.DS_Store
RIM_interpret/__init__.py
rim_interpret-0.0.5.dist-info/METADATA
rim_interpret-0.0.5.dist-info/WHEEL
rim_interpret-0.0.5.dist-info/licenses/LICENSE
rim_interpret-0.0.5.dist-info/RECORD
