Metadata-Version: 2.1
Name: RIM-interpret
Version: 0.0.5
Summary: Interpretability metrics for machine learning models
Project-URL: Homepage, https://github.com/xloffree/RIM-interpret
Project-URL: Bug Tracker, https://github.com/xloffree/RIM-interpret/issues
Author-email: Xavier Loffree <Xavix500@gmail.com>
License-File: LICENSE
Keywords: interpretability,lime,machine learning,modelling,omics,permutation feature importance,rim,shap
Classifier: License :: OSI Approved :: MIT License
Classifier: Operating System :: OS Independent
Classifier: Programming Language :: Python :: 3
Requires-Python: >=3.7
Requires-Dist: hatchling
Requires-Dist: lime
Requires-Dist: numpy
Requires-Dist: pandas
Requires-Dist: pytest
Requires-Dist: scikit-learn
Requires-Dist: shap
